{
	"Moves": [
		{
			"move_id": "1",
			"name": "Darkness",
			"power": "30",
      "condition_chance": "0.3",
      "description": "Base damage: 30 Special Condition Chance: 30%"
		},
    {
      "move_id": "2",
      "name": "Shadow Ball",
      "power": "75",
      "condition_chance": "0",
      "description": "Base damage: 75 Special Condition Chance: 0%"
    },
    {
      "move_id": "3",
      "name": "Vine Whip",
      "power": "75",
      "condition_chance": "0",
      "description": "Base damage: 75 Special Condition Chance: 0%"
    },
    {
      "move_id": "4",
      "name": "Wood Sword",
      "power": "50",
      "condition_chance": "0",
      "description": "Base damage: 50 Special Condition Chance: 0%"
    },
    {
      "move_id": "5",
      "name": "Flood",
      "power": "40",
      "condition_chance": "0",
      "description": "Base damage: 40 Special Condition Chance: 0%"
    },
    {
      "move_id": "6",
      "name": "Water Jet",
      "power": "90",
      "condition_chance": "0",
      "description": "Base damage: 90 Special Condition Chance: 0%"
    },
    {
      "move_id": "7",
      "name": "Burn",
      "power": "30",
      "condition_chance": "0.3",
      "description": "Base damage: 30 Special Condition Chance: 30%"
    },
    {
      "move_id": "8",
      "name": "Flame pillar",
      "power": "60",
      "condition_chance": "0",
      "description": "Base damage: 60 Special Condition Chance: 0%"
    },
    {
      "move_id": "9",
      "name": "Sky Scale",
      "power": "75",
      "condition_chance": "0",
      "description": "Base damage: 75 Special Condition Chance: 0%"
    },
    {
      "move_id": "10",
      "name": "Wind Barrage",
      "power": "45",
      "condition_chance": "0",
      "description": "Base damage: 45 Special Condition Chance: 0%"
    },
    {
      "move_id": "11",
      "name": "Holy Blindness",
      "power": "15",
      "condition_chance": "0.9",
      "description": "Base damage: 15 Special Condition Chance: 90%"
    },
    {
      "move_id": "12",
      "name": "Purify",
      "power": "75",
      "condition_chance": "0",
      "description": "Base damage: 75 Special Condition Chance: 0%"
    },
    {
      "move_id": "13",
      "name": "slime",
      "power": "45",
      "condition_chance": "0",
      "description": "Base damage: 45 Special Condition Chance: 0%"
    },
    {
      "move_id": "14",
      "name": "slime slap",
      "power": "55",
      "condition_chance": "0.5",
      "description": "Base damage: 55 Special Condition Chance: 50%"
    },
    {
      "move_id": "15",
      "name": "DeVito Breath",
      "power": "60",
      "condition_chance": "0",
      "description": "Base damage: 60 Special Condition Chance: 0%"
    },
    {
      "move_id": "16",
      "name": "DeVito Punch",
      "power": "50",
      "condition_chance": "0.5",
      "description": "Base damage: 50 Special Condition Chance: 50%"
    },
    {
      "move_id": "17",
      "name": "bad motha-fucker",
      "power": "70",
      "condition_chance": "0",
      "description": "Base damage: 70 Special Condition Chance: 0%"
    },
    {
      "move_id": "18",
      "name": "gun",
      "power": "80",
      "condition_chance": "0.5",
      "description": "Base damage: 80 Special Condition Chance: 50%"
    }
	]
}